pjt/__init__.py
pjt/translator.py
protobuf_json_translate-0.0.1.dist-info/LICENSE
protobuf_json_translate-0.0.1.dist-info/METADATA
protobuf_json_translate-0.0.1.dist-info/WHEEL
protobuf_json_translate-0.0.1.dist-info/top_level.txt
protobuf_json_translate-0.0.1.dist-info/RECORD
